is_number/__init__.py
is_number/_version.py
is_number/is_float.py
is_number/is_number.py
is_number-0.0.3.dist-info/LICENSE
is_number-0.0.3.dist-info/METADATA
is_number-0.0.3.dist-info/WHEEL
is_number-0.0.3.dist-info/top_level.txt
is_number-0.0.3.dist-info/RECORD
