Metadata-Version: 2.1
Name: is-number
Version: 0.0.3
Summary: A Python library to determine if something is a number.
Home-page: UNKNOWN
Author: Jacob Tomlinson
Author-email: jacob@tomlinson.email
License: UNKNOWN
Platform: UNKNOWN
Classifier: Programming Language :: Python :: 3
Classifier: License :: OSI Approved :: MIT License
Classifier: Operating System :: OS Independent
Requires-Python: >=3.6
